{"rules":[{"left":"TOP","right":["S_VP","PUNC"]},{"left":"S_VP","right":["VB","NP"]},{"left":"VB","right":["List"]},{"left":"NP","right":["NP'","SBAR"]},{"left":"NP'","right":["NP'","PP"]},{"left":"NP'","right":["NP","PP"]},{"left":"NP","right":["DT","NNS"]},{"left":"DT","right":["the"]},{"left":"NNS","right":["flights"]},{"left":"PP","right":["IN","NP_NNP"]},{"left":"IN","right":["from"]},{"left":"NP_NNP","right":["Baltimore"]},{"left":"PP","right":["TO","NP_NNP"]},{"left":"TO","right":["to"]},{"left":"NP_NNP","right":["Seattle"]},{"left":"SBAR","right":["WHNP_WDT","S_VP"]},{"left":"WHNP_WDT","right":["that"]},{"left":"S_VP","right":["VBP","PP"]},{"left":"VBP","right":["stop"]},{"left":"PP","right":["IN","NP_NNP"]},{"left":"IN","right":["in"]},{"left":"NP_NNP","right":["Minneapolis"]},{"left":"PUNC","right":["."]}]}
